redpocket/__init__.py
redpocket/__main__.py
redpocket/api.py
redpocket/exceptions.py
python_redpocket-0.3.1.dist-info/LICENSE
python_redpocket-0.3.1.dist-info/WHEEL
python_redpocket-0.3.1.dist-info/METADATA
python_redpocket-0.3.1.dist-info/RECORD
