Metadata-Version: 2.1
Name: python-redpocket
Version: 0.3.1
Summary: A Python API Interface for RedPocket Mobile
Home-page: https://github.com/mbillow/python-redpocket
License: MIT
Author: Marc Billow
Author-email: marc@billow.me
Requires-Python: >=3.8,<4.0
Classifier: Intended Audience :: End Users/Desktop
Classifier: License :: OSI Approved :: MIT License
Classifier: Natural Language :: English
Classifier: Operating System :: OS Independent
Classifier: Programming Language :: Python :: 3
Classifier: Programming Language :: Python :: 3.8
Classifier: Programming Language :: Python :: 3.9
Requires-Dist: requests (>=2.25.1,<3.0.0)
Project-URL: Documentation, https://github.com/mbillow/python-redpocket
Project-URL: Repository, https://github.com/mbillow/python-redpocket
